odoo/addons/sale_stock_product_pack/README.rst
odoo/addons/sale_stock_product_pack/__init__.py
odoo/addons/sale_stock_product_pack/__manifest__.py
odoo/addons/sale_stock_product_pack/i18n/it.po
odoo/addons/sale_stock_product_pack/i18n/sale_stock_product_pack.pot
odoo/addons/sale_stock_product_pack/models/__init__.py
odoo/addons/sale_stock_product_pack/models/sale_order.py
odoo/addons/sale_stock_product_pack/readme/CONTRIBUTORS.md
odoo/addons/sale_stock_product_pack/readme/DESCRIPTION.md
odoo/addons/sale_stock_product_pack/readme/ROADMAP.md
odoo/addons/sale_stock_product_pack/static/description/icon.png
odoo/addons/sale_stock_product_pack/static/description/index.html
odoo/addons/sale_stock_product_pack/tests/__init__.py
odoo/addons/sale_stock_product_pack/tests/test_sale_stock_product_pack.py
odoo_addon_sale_stock_product_pack-18.0.1.0.1.dist-info/METADATA
odoo_addon_sale_stock_product_pack-18.0.1.0.1.dist-info/WHEEL
odoo_addon_sale_stock_product_pack-18.0.1.0.1.dist-info/top_level.txt
odoo_addon_sale_stock_product_pack-18.0.1.0.1.dist-info/RECORD
