Metadata-Version: 2.1
Name: odoo-addon-sale_stock_product_pack
Version: 18.0.1.0.1
Requires-Python: >=3.10
Requires-Dist: odoo-addon-sale_product_pack==18.0.*
Requires-Dist: odoo-addon-stock_product_pack==18.0.*
Requires-Dist: odoo==18.0.*
Summary: Compatibility module for packs that are storable products
Home-page: https://github.com/OCA/product-pack
License: AGPL-3
Author: Tecnativa, Odoo Community Association (OCA)
Author-email: support@odoo-community.org
Classifier: Programming Language :: Python
Classifier: Framework :: Odoo
Classifier: Framework :: Odoo :: 18.0
Classifier: License :: OSI Approved :: GNU Affero General Public License v3
Classifier: Development Status :: 4 - Beta
